iso8601utils/__init__.py
iso8601utils/duration.py
iso8601utils/interval.py
iso8601utils/match.py
iso8601utils/parsers.py
iso8601utils/regex.py
iso8601utils/tz.py
iso8601utils/validators.py
iso8601utils-0.1.2.dist-info/DESCRIPTION.rst
iso8601utils-0.1.2.dist-info/LICENSE.txt
iso8601utils-0.1.2.dist-info/METADATA
iso8601utils-0.1.2.dist-info/RECORD
iso8601utils-0.1.2.dist-info/WHEEL
iso8601utils-0.1.2.dist-info/metadata.json
iso8601utils-0.1.2.dist-info/top_level.txt
