Metadata-Version: 2.0
Name: iso8601utils
Version: 0.1.2
Summary: Utilities for parsing ISO 8601 times, dates, datetimes, intervals, and durations
Home-page: https://github.com/silverfernsys/iso8601utils
Author: Silver Fern Systems
Author-email: dev@silverfern.io
License: BSD
Keywords: iso8601 time date datetime duration interval
Platform: UNKNOWN
Classifier: Development Status :: 3 - Alpha
Classifier: Intended Audience :: Developers
Classifier: License :: OSI Approved :: BSD License
Classifier: Programming Language :: Python :: 2.7
Classifier: Programming Language :: Python :: 3.0
Classifier: Programming Language :: Python :: 3.1
Classifier: Programming Language :: Python :: 3.2
Classifier: Programming Language :: Python :: 3.3
Classifier: Programming Language :: Python :: 3.4
Classifier: Programming Language :: Python :: 3.5
Classifier: Programming Language :: Python :: 3.6
Requires-Dist: enum34
Requires-Dist: monthdelta (==1.0b)
Provides-Extra: test
Requires-Dist: codecov; extra == 'test'
Requires-Dist: coverage; extra == 'test'
Requires-Dist: mock; extra == 'test'
Requires-Dist: pytest; extra == 'test'
